flask_debugtoolbar_sqlalchemy/__init__.py
flask_debugtoolbar_sqlalchemy/panel.py
flask_debugtoolbar_sqlalchemy/templates/sql_panel.html
flask_debugtoolbar_sqlalchemy-0.2.0.dist-info/LICENSE
flask_debugtoolbar_sqlalchemy-0.2.0.dist-info/METADATA
flask_debugtoolbar_sqlalchemy-0.2.0.dist-info/WHEEL
flask_debugtoolbar_sqlalchemy-0.2.0.dist-info/top_level.txt
flask_debugtoolbar_sqlalchemy-0.2.0.dist-info/RECORD
