Metadata-Version: 2.1
Name: flask-debugtoolbar-sqlalchemy
Version: 0.2.0
Summary: Flask Debug Toolbar panel for SQLAlchemy
Home-page: https://git.sr.ht/~ihabunek/flask_debugtoolbar_sqlalchemy
Author: Ivan Habunek
Author-email: ivan@habunek.com
License: GPL-3
Keywords: flask debug toolbar sqlalchemy panel
Platform: UNKNOWN
Classifier: Framework :: Flask
Classifier: License :: OSI Approved :: GNU General Public License v3 (GPLv3)
Classifier: Programming Language :: Python :: 3 :: Only
